trigger.py
version.py
vaccine_notifier-0.0.6.dist-info/LICENSE
vaccine_notifier-0.0.6.dist-info/METADATA
vaccine_notifier-0.0.6.dist-info/WHEEL
vaccine_notifier-0.0.6.dist-info/entry_points.txt
vaccine_notifier-0.0.6.dist-info/top_level.txt
vaccine_notifier-0.0.6.dist-info/RECORD
