Metadata-Version: 2.1
Name: vaccine-notifier
Version: 0.0.6
Summary: Notify vaccination availability - Play Music/Song and Send Desktop Notifaction for vaccine availability
Home-page: https://github.com/panchal999/vaccine-notifier
Author: Parth Panchal
Author-email: parthnp98@gmail.com
License: UNKNOWN
Platform: UNKNOWN
License-File: LICENSE
Requires-Dist: requests (>=2.25.1)
Requires-Dist: pydub (>=0.3.3)
Requires-Dist: notify-py (>=0.3.3)
Provides-Extra: dev
Requires-Dist: wheel (>=0.34.2) ; extra == 'dev'
Requires-Dist: twine (>=3.1.1) ; extra == 'dev'
Requires-Dist: pip-tools (>=4.4.1) ; extra == 'dev'
